mcp_server_github_trending/__init__.py
mcp_server_github_trending/__main__.py
mcp_server_github_trending/server.py
mcp_github_trending-0.1.0.dist-info/METADATA
mcp_github_trending-0.1.0.dist-info/WHEEL
mcp_github_trending-0.1.0.dist-info/entry_points.txt
mcp_github_trending-0.1.0.dist-info/licenses/LICENSE
mcp_github_trending-0.1.0.dist-info/RECORD
