Metadata-Version: 2.4
Name: mcp-github-trending
Version: 0.1.0
Summary: A Model Context Protocol server providing GitHub trending repositories information for LLMs
Author-email: He Tao <hetao7@pku.edu.cn>
License: MIT
License-File: LICENSE
Keywords: github,llm,mcp,trending
Classifier: Development Status :: 4 - Beta
Classifier: Intended Audience :: Developers
Classifier: License :: OSI Approved :: MIT License
Classifier: Programming Language :: Python :: 3
Classifier: Programming Language :: Python :: 3.12
Requires-Python: >=3.12
Requires-Dist: gtrending>=0.5.1
Requires-Dist: mcp>=1.0.0
Requires-Dist: pydantic>=2.0.0
